{"title":"Chloe Large Lucy","brand":"Chloe","price":6480.0,"sale_price":null,"previous_price":6480.0,"sizes":[],"description":"Effortlessly chic, the Large Lucy demonstrates the classic Parisian chic aesthetic of the Chloe house, offering elegance to the everyday.","main_image":"http://shop.davidjones.com.au/djimages/5131-405189_HONEY_01_330x430.jpg","sku":"633521","colors":[],"materials":[],"category":"Bag Checklist","url":"http:_shop.davidjones.com.au_djs_en_davidjones_shoes-accessories_bag-checklist_large-lucy-5131-405189--1","discount":0,"id":"http:_shop.davidjones.com.au_djs_en_davidjones_shoes-accessories_bag-checklist_large-lucy-5131-405189--1"}