{"title":"Blazer George Check Longsleeve Shirt","brand":"Blazer","price":178.0,"sale_price":null,"previous_price":178.0,"sizes":["","L","M","XL","XXL"],"description":"This trim-fitting sport shirt is crafted from crisp, lightweight cotton broadcloth and features a handsome tartan motif.","main_image":"http://shop.davidjones.com.au/djimages/3498-106985_NAVY_01_330x430.jpg","sku":"943520","colors":[],"materials":["Cotton"],"category":"Colour Watch: Blues & Greens","url":"http:_shop.davidjones.com.au_djs_en_davidjones_george-check-longsleeve-shirt","discount":0,"id":"http:_shop.davidjones.com.au_djs_en_davidjones_george-check-longsleeve-shirt"}