{"title":"Annapelle Leather Medium Dakota Wallet","brand":"Annapelle","price":118.0,"sale_price":null,"previous_price":118.0,"sizes":[],"description":"This minimalist leather women's wallet features stitching detail, simple tab clasp and room for 12 cards.","main_image":"http://shop.davidjones.com.au/djimages/5377-79607_RED_01_330x430.jpg","sku":"130507","colors":[],"materials":[],"category":"Women's Handbags & Wallets","url":"http:_shop.davidjones.com.au_djs_en_davidjones_leather-medium-dakota-wallet","discount":0,"id":"http:_shop.davidjones.com.au_djs_en_davidjones_leather-medium-dakota-wallet"}