{"title":"Bec & Bridge Estella Peplum Top","brand":"Bec & Bridge","price":260.0,"sale_price":null,"previous_price":260.0,"sizes":["","10","12","6","8"],"description":"Work fashion's penchant for peplums day or night with Bec & Bridge's Estella top. Cut from textured waffle ponte, it will add a tactile touch to any outfit.","main_image":"http://shop.davidjones.com.au/djimages/1666-726739_WHITE_01_330x430.jpg","sku":"897523","colors":[],"materials":["Polyester","SpandexModel"],"category":"Bec & Bridge","url":"http:_shop.davidjones.com.au_djs_en_davidjones_estella-peplum-top","discount":0,"id":"http:_shop.davidjones.com.au_djs_en_davidjones_estella-peplum-top"}