{"title":"American Tourister Astronolite Upright 55cm","brand":"American Tourister","price":296.0,"sale_price":148.85,"previous_price":229.0,"sizes":["","Blue","Grey","Red"],"description":"Astrono-lite is a hybrid line with a combination of a strong, hard shell at the back and flexible, soft fabric at the front.","main_image":"http://shop.davidjones.com.au/djimages/3896-102177_Red_01_330x430.jpg","sku":"72679","colors":[],"materials":[],"category":"Luggage & Travel Accessories","url":"http:_shop.davidjones.com.au_djs_en_davidjones_astrono-lite-upright-55cm","discount":-29.25764192139738,"sale":true,"id":"http:_shop.davidjones.com.au_djs_en_davidjones_astrono-lite-upright-55cm"}