{"title":"Skip Hop Octopus Ring Toss Fountain","brand":"Skip Hop","price":38.0,"sale_price":null,"previous_price":38.0,"sizes":[],"description":"Engage and enthuse young ones with this adorable Octopus Foundation, making bath time more like play time.","main_image":"http://shop.davidjones.com.au/djimages/9868-653550_NA_01_330x430.jpg","sku":"424543","colors":[],"materials":[],"category":"Baby Skincare & Bath","url":"http:_shop.davidjones.com.au_djs_en_davidjones_children_baby-skincare-bath_octopus-ring-toss-fountain","discount":0,"id":"http:_shop.davidjones.com.au_djs_en_davidjones_children_baby-skincare-bath_octopus-ring-toss-fountain"}