{"title":"Smeg SA37X Microwave Oven","brand":"Smeg","price":1138.0,"sale_price":569.0,"previous_price":690.0,"sizes":[],"description":"Combining high-performance technology with style, this stainless steel microwave from Smeg offers multiple functions such as sequence programming, one-touch cooking, a dish warmer and speedy cook.","main_image":"http://shop.davidjones.com.au/djimages/7662-82080_NoColour_01_330x430.jpg","sku":"229097","colors":[],"materials":[],"category":"Large Appliances","url":"http:_shop.davidjones.com.au_djs_en_davidjones_home-leisure_large-appliances_sa37x-microwave-oven","discount":-64.92753623188406,"sale":true,"id":"http:_shop.davidjones.com.au_djs_en_davidjones_home-leisure_large-appliances_sa37x-microwave-oven"}