{"title":"Barbie Barbie Glam Pool","brand":"Barbie","price":34.0,"sale_price":17.46,"previous_price":24.95,"sizes":[],"description":"Make a stylish splash in the barbie glam pool. This exciting set with funky accessories means there is always time for more fun in the sun.","main_image":"http://shop.davidjones.com.au/djimages/9868-665199_NA_01_330x430.jpg","sku":"386535","colors":[],"materials":[],"category":"Gifts for Children","url":"http:_shop.davidjones.com.au_djs_en_davidjones_barbie-glam-pool","discount":-36.272545090180365,"sale":true,"id":"http:_shop.davidjones.com.au_djs_en_davidjones_barbie-glam-pool"}