{"title":"Aesop B Triple C Facial Balancing Gel 60ml","brand":"Aesop","price":240.0,"sale_price":null,"previous_price":240.0,"sizes":[],"description":"Silicone-free moisturising and skin-balancing gel for oily, combination and sensitive skin types.","main_image":"http://shop.davidjones.com.au/djimages/2727-13687_NA_01_330x430.jpg","sku":"13016","colors":[],"materials":[],"category":"Men's Fragrance & Grooming","url":"http:_shop.davidjones.com.au_djs_en_davidjones_b-triple-c-facial-balancing-gel-60ml","discount":0,"id":"http:_shop.davidjones.com.au_djs_en_davidjones_b-triple-c-facial-balancing-gel-60ml"}