{"title":"All About Eve The City Tee","brand":"All About Eve","price":58.0,"sale_price":null,"previous_price":58.0,"sizes":[],"description":"Featuring some of the world's most famous buildings in print, this girls long sleeve tee is a perfect layering piece for cooler seasons.","main_image":"http://shop.davidjones.com.au/djimages/4800-200185_WHITE_01_330x430.jpg","sku":"975048","colors":[],"materials":["Cotton-"],"category":"Girls","url":"http:_shop.davidjones.com.au_djs_en_davidjones_children_girls_the-city-tee","discount":0,"id":"http:_shop.davidjones.com.au_djs_en_davidjones_children_girls_the-city-tee"}